README.md
setup.py
disnake/ext/dashboard/__init__.py
disnake/ext/dashboard/dashboard.py
disnake/ext/dashboard/errors.py
disnake/ext/dashboard/server.py
disnake_ext_dashboard.egg-info/PKG-INFO
disnake_ext_dashboard.egg-info/SOURCES.txt
disnake_ext_dashboard.egg-info/dependency_links.txt
disnake_ext_dashboard.egg-info/requires.txt
disnake_ext_dashboard.egg-info/top_level.txt