Metadata-Version: 2.1
Name: disnake-ext-dashboard
Version: 0.3.2
Summary: Веб-перехватчик и расширение disnake на основе запросов для создания панели управления ботом.
Home-page: https://github.com/MaseZev/disnake-ext-dashboard
Author: MaseZev
License: MIT
Platform: UNKNOWN
Classifier: Natural Language :: English
Classifier: Operating System :: OS Independent
Classifier: Programming Language :: Python :: 3.8
Classifier: Topic :: Internet
Classifier: Topic :: Software Development :: Libraries
Classifier: Topic :: Software Development :: Libraries :: Python Modules
Classifier: Topic :: Utilities
Requires-Python: >=3.8.0
